{
  "description": "备件管理系统 - 微信小程序",
  "packOptions": {
    "ignore": [],
    "include": [
      { "type": "folder", "value": "custom-tab-bar" }
    ]
  },
  "setting": {
    "bundle": false,
    "userConfirmedBundleSwitch": false,
    "urlCheck": true,
    "scopeDataCheck": false,
    "coverView": true,
    "es6": true,
    "postcss": true,
    "compileHotReLoad": false,
    "lazyloadPlaceholderEnable": false,
    "preloadBackgroundData": false,
    "minified": true,
    "autoAudits": false,
    "newFeature": false,
    "uglifyFileName": false,
    "uploadWithSourceMap": true,
    "useIsolateContext": true,
    "nodeModules": false,
    "enhance": true,
    "useMultiFrameRuntime": true,
    "useApiHook": true,
    "useApiHostProcess": true,
    "showShadowRootInWx498": true,
    "packNpmManually": false,
    "enableEngineNative": false,
    "packNpmRelationList": [],
    "minifyWXSS": true,
    "showES6CompileOption": false,
    "minifyWXML": true,
    "ignoreDevUnusedFiles": false,
    "ignoreUploadUnusedFiles": false,
    "babelSetting": {
      "ignore": [],
      "disablePlugins": [],
      "outputPath": ""
    }
  },
  "compileType": "miniprogram",
  "condition": {},
  "editorSetting": {
    "tabIndent": "insertSpaces",
    "tabSize": 2
  },
  "libVersion": "3.3.4",
  "appid": "wxa5d538f2c997e7fc",
  "projectname": "spare-parts-mp",
  "cloudfunctionRoot": "cloudfunctions/",
  "miniprogramRoot": "",
  "srcMiniprogramRoot": ""
}
